h5_info/__init__.py
h5_info/camera_image.py
h5_info/constants.py
h5_info/errors.py
h5_info/geo.py
h5_info/lidar_image.py
h5_info/logger.py
h5_info/multispectral_camera_image.py
h5_info/plot.py
h5_info/position.py
h5_info/sensor.py
h5_info/session.py
h5_info/utils.py
h5_info/vector.py
h5_info_pkg_inra_phenome-1.3.4.dist-info/LICENSE
h5_info_pkg_inra_phenome-1.3.4.dist-info/METADATA
h5_info_pkg_inra_phenome-1.3.4.dist-info/WHEEL
h5_info_pkg_inra_phenome-1.3.4.dist-info/top_level.txt
h5_info_pkg_inra_phenome-1.3.4.dist-info/RECORD
