Metadata-Version: 2.1
Name: h5-info-pkg-inra-phenome
Version: 1.3.4
Summary: Utility package for extracting, reading and saving metadata from HDF5 Phenomobile V2, Phenoverger and LITERAL acquisition files
Home-page: https://forgemia.inra.fr/4p/tools/h5info
Author: Eric David
Author-email: eric.david@ephesia-consult.com
License: UNKNOWN
Platform: UNKNOWN
Classifier: Programming Language :: Python :: 3
Classifier: License :: OSI Approved :: MIT License
Classifier: Operating System :: OS Independent
Requires-Python: >=3.8
License-File: LICENSE
Requires-Dist: h5py
Requires-Dist: Pillow
